odoo9_addon_l10n_ch_bank-9.0.1.0.1-py2.7-nspkg.pth
odoo9_addon_l10n_ch_bank-9.0.1.0.1.dist-info/DESCRIPTION.rst
odoo9_addon_l10n_ch_bank-9.0.1.0.1.dist-info/METADATA
odoo9_addon_l10n_ch_bank-9.0.1.0.1.dist-info/RECORD
odoo9_addon_l10n_ch_bank-9.0.1.0.1.dist-info/WHEEL
odoo9_addon_l10n_ch_bank-9.0.1.0.1.dist-info/metadata.json
odoo9_addon_l10n_ch_bank-9.0.1.0.1.dist-info/namespace_packages.txt
odoo9_addon_l10n_ch_bank-9.0.1.0.1.dist-info/top_level.txt
odoo_addons/l10n_ch_bank/README.rst
odoo_addons/l10n_ch_bank/__init__.py
odoo_addons/l10n_ch_bank/__openerp__.py
odoo_addons/l10n_ch_bank/data/res.bank.csv
odoo_addons/l10n_ch_bank/i18n/de.po
odoo_addons/l10n_ch_bank/i18n/es.po
odoo_addons/l10n_ch_bank/i18n/fi.po
odoo_addons/l10n_ch_bank/i18n/fr.po
odoo_addons/l10n_ch_bank/i18n/it.po
odoo_addons/l10n_ch_bank/i18n/nb_NO.po
odoo_addons/l10n_ch_bank/i18n/sl.po
odoo_addons/l10n_ch_bank/migrations/8.0.9.0.0/pre-migration.py
odoo_addons/l10n_ch_bank/migrations/9.0.9.0.0/pre-migration.py
odoo_addons/l10n_ch_bank/models/__init__.py
odoo_addons/l10n_ch_bank/models/bank.py
odoo_addons/l10n_ch_bank/static/description/icon.png
